send_ip/__init__.py
send_ip/send_ip.py
send_ip/setup_cron.py
send_ip-0.0.10.dist-info/LICENSE
send_ip-0.0.10.dist-info/METADATA
send_ip-0.0.10.dist-info/WHEEL
send_ip-0.0.10.dist-info/top_level.txt
send_ip-0.0.10.dist-info/RECORD
