Metadata-Version: 2.1
Name: send_ip
Version: 0.0.10
Summary: python package to send its own IP to another machine through ssh
Home-page: https://github.com/matiasandina/send_ip
Author: Matias Andina
Author-email: Matias Andina <matiasandina@gmail.com>
License: MIT License
Project-URL: Homepage, https://github.com/matiasandina/send_ip
Classifier: Programming Language :: Python :: 3
Classifier: Programming Language :: Python :: 3.7
Classifier: Programming Language :: Python :: 3.8
Classifier: Programming Language :: Python :: 3.9
Classifier: License :: OSI Approved :: MIT License
Classifier: Operating System :: OS Independent
License-File: LICENSE
Requires-Dist: PyYAML >=5.3.1
Requires-Dist: paramiko >=2.6.0
Requires-Dist: python-crontab >=0.23.0
Requires-Dist: py-console
Requires-Dist: scp
Provides-Extra: dev
Requires-Dist: twine ; extra == 'dev'
Requires-Dist: check-manifest ; extra == 'dev'
Requires-Dist: PyYAML ==5.3.1 ; extra == 'dev'
Requires-Dist: paramiko ==2.6.0 ; extra == 'dev'
